terrabridge/__init__.py
terrabridge/base.py
terrabridge/gcp/__init__.py
terrabridge/gcp/base.py
terrabridge/gcp/bigquery.py
terrabridge/gcp/bigtable.py
terrabridge/gcp/cloud_sql.py
terrabridge/gcp/cloud_sql.pyi
terrabridge/gcp/cloud_tasks.py
terrabridge/gcp/gcs_bucket.py
terrabridge/gcp/gcs_bucket.pyi
terrabridge/gcp/pubsub.py
terrabridge/gcp/pubsub_lite.py
terrabridge/gcp/secret_manager.py
terrabridge/parser.py
terrabridge/utils.py
terrabridge-0.0.1.dev3.dist-info/METADATA
terrabridge-0.0.1.dev3.dist-info/WHEEL
terrabridge-0.0.1.dev3.dist-info/RECORD
