Metadata-Version: 2.1
Name: terrabridge
Version: 0.0.1.dev3
Summary: terrabridge connects your terraform managed resources to your application.
License: Apache-2.0
Author: CalebTVanDyke
Author-email: ctvandyke24@gmail.com
Requires-Python: >=3.8,<4.0
Classifier: License :: OSI Approved :: Apache Software License
Classifier: Programming Language :: Python :: 3
Classifier: Programming Language :: Python :: 3.8
Classifier: Programming Language :: Python :: 3.9
Classifier: Programming Language :: Python :: 3.10
Classifier: Programming Language :: Python :: 3.11
Classifier: Programming Language :: Python :: 3.12
Requires-Dist: asyncpg[dev] (>=0.29.0,<0.30.0)
Requires-Dist: cloud-sql-python-connector[gcp]
Requires-Dist: coverage[dev] (>=7.4.0,<8.0.0)
Requires-Dist: fsspec
Requires-Dist: gcsfs
Requires-Dist: google-cloud-pubsub[gcp]
Requires-Dist: google-cloud-pubsublite[gcp]
Requires-Dist: google-cloud-secret-manager[gcp]
Requires-Dist: google-cloud-storage[gcp]
Requires-Dist: pg8000[dev] (>=1.30.4,<2.0.0)
Requires-Dist: pymysql[dev] (>=1.1.0,<2.0.0)
Requires-Dist: pytest-asyncio[dev] (>=0.23.3,<0.24.0)
Requires-Dist: pytest-cov[dev] (>=4.1.0,<5.0.0)
Requires-Dist: pytest[dev] (>=7.4.4,<8.0.0)
Requires-Dist: python-tds[dev] (>=1.14.0,<2.0.0)
Requires-Dist: s3fs
Requires-Dist: sqlalchemy-pytds[dev] (>=1.0.0,<2.0.0)
Requires-Dist: sqlalchemy[dev] (>=2.0.25,<3.0.0)
